{"fixture":{"id":868229,"referee":"A. Madley","timezone":"UTC","date":"2023-04-01T16:30:00+00:00","timestamp":1680366600,"periods":{"first":1680366600,"second":1680370200},"venue":{"id":519,"name":"Stamford Bridge","city":"London"},"status":{"long":"Match Finished","short":"FT","elapsed":90,"extra":null}},"league":{"id":39,"name":"Premier League","country":"England","logo":"https:\/\/media.api-sports.io\/football\/leagues\/39.png","flag":"https:\/\/media.api-sports.io\/flags\/gb-eng.svg","season":2022,"round":"Regular Season - 29","standings":true},"teams":{"home":{"id":49,"name":"Chelsea","logo":"https:\/\/media.api-sports.io\/football\/teams\/49.png","winner":false},"away":{"id":66,"name":"Aston Villa","logo":"https:\/\/media.api-sports.io\/football\/teams\/66.png","winner":true}},"goals":{"home":0,"away":2},"score":{"halftime":{"home":0,"away":1},"fulltime":{"home":0,"away":2},"extratime":{"home":null,"away":null},"penalty":{"home":null,"away":null}},"events":[{"time":{"elapsed":4,"extra":null},"team":{"id":66,"name":"Aston Villa","logo":"https:\/\/media.api-sports.io\/football\/teams\/66.png"},"player":{"id":1904,"name":"Boubacar Kamara"},"assist":{"id":null,"name":null},"type":"Card","detail":"Yellow Card","comments":"Foul"},{"time":{"elapsed":18,"extra":null},"team":{"id":66,"name":"Aston Villa","logo":"https:\/\/media.api-sports.io\/football\/teams\/66.png"},"player":{"id":19366,"name":"O. Watkins"},"assist":{"id":null,"name":null},"type":"Goal","detail":"Normal Goal","comments":null},{"time":{"elapsed":39,"extra":null},"team":{"id":49,"name":"Chelsea","logo":"https:\/\/media.api-sports.io\/football\/teams\/49.png"},"player":{"id":2291,"name":"Mateo Kova\u010di\u0107"},"assist":{"id":null,"name":null},"type":"Card","detail":"Yellow Card","comments":"Foul"},{"time":{"elapsed":46,"extra":null},"team":{"id":66,"name":"Aston Villa","logo":"https:\/\/media.api-sports.io\/football\/teams\/66.png"},"player":{"id":1904,"name":"B. Kamara"},"assist":{"id":19016,"name":"C. Chambers"},"type":"subst","detail":"Substitution 1","comments":null},{"time":{"elapsed":54,"extra":null},"team":{"id":49,"name":"Chelsea","logo":"https:\/\/media.api-sports.io\/football\/teams\/49.png"},"player":{"id":2933,"name":"Ben Chilwell"},"assist":{"id":null,"name":null},"type":"Card","detail":"Yellow Card","comments":"Foul"},{"time":{"elapsed":56,"extra":null},"team":{"id":66,"name":"Aston Villa","logo":"https:\/\/media.api-sports.io\/football\/teams\/66.png"},"player":{"id":19191,"name":"J.  McGinn"},"assist":{"id":19192,"name":"J. Ramsey"},"type":"Goal","detail":"Normal Goal","comments":null},{"time":{"elapsed":57,"extra":null},"team":{"id":49,"name":"Chelsea","logo":"https:\/\/media.api-sports.io\/football\/teams\/49.png"},"player":{"id":63577,"name":"M. Mudryk"},"assist":{"id":136723,"name":"N. Madueke"},"type":"subst","detail":"Substitution 1","comments":null},{"time":{"elapsed":57,"extra":null},"team":{"id":49,"name":"Chelsea","logo":"https:\/\/media.api-sports.io\/football\/teams\/49.png"},"player":{"id":2292,"name":"R. Loftus-Cheek"},"assist":{"id":2290,"name":"N. Kant\u00e9"},"type":"subst","detail":"Substitution 2","comments":null},{"time":{"elapsed":61,"extra":null},"team":{"id":49,"name":"Chelsea","logo":"https:\/\/media.api-sports.io\/football\/teams\/49.png"},"player":{"id":583,"name":"Jo\u00e3o F\u00e9lix"},"assist":{"id":null,"name":null},"type":"Var","detail":"Penalty cancelled","comments":null},{"time":{"elapsed":68,"extra":null},"team":{"id":49,"name":"Chelsea","logo":"https:\/\/media.api-sports.io\/football\/teams\/49.png"},"player":{"id":5996,"name":"Enzo Fern\u00e1ndez"},"assist":{"id":null,"name":null},"type":"Card","detail":"Yellow Card","comments":"Foul"},{"time":{"elapsed":76,"extra":null},"team":{"id":66,"name":"Aston Villa","logo":"https:\/\/media.api-sports.io\/football\/teams\/66.png"},"player":{"id":19071,"name":"E. Buend\u00eda"},"assist":{"id":983,"name":"L. Bailey"},"type":"subst","detail":"Substitution 2","comments":null},{"time":{"elapsed":80,"extra":null},"team":{"id":49,"name":"Chelsea","logo":"https:\/\/media.api-sports.io\/football\/teams\/49.png"},"player":{"id":2291,"name":"M. Kova\u010di\u0107"},"assist":{"id":67972,"name":"C. Gallagher"},"type":"subst","detail":"Substitution 3","comments":null},{"time":{"elapsed":80,"extra":null},"team":{"id":49,"name":"Chelsea","logo":"https:\/\/media.api-sports.io\/football\/teams\/49.png"},"player":{"id":47380,"name":"Marc Cucurella"},"assist":{"id":17,"name":"C. Puli\u0161i\u0107"},"type":"subst","detail":"Substitution 4","comments":null},{"time":{"elapsed":84,"extra":null},"team":{"id":66,"name":"Aston Villa","logo":"https:\/\/media.api-sports.io\/football\/teams\/66.png"},"player":{"id":19016,"name":"Calum Chambers"},"assist":{"id":null,"name":null},"type":"Card","detail":"Yellow Card","comments":"Time wasting"},{"time":{"elapsed":87,"extra":null},"team":{"id":66,"name":"Aston Villa","logo":"https:\/\/media.api-sports.io\/football\/teams\/66.png"},"player":{"id":47522,"name":"Douglas Luiz"},"assist":{"id":2922,"name":"L. Dendoncker"},"type":"subst","detail":"Substitution 3","comments":null},{"time":{"elapsed":89,"extra":null},"team":{"id":66,"name":"Aston Villa","logo":"https:\/\/media.api-sports.io\/football\/teams\/66.png"},"player":{"id":47547,"name":"\u00c1lex Moreno"},"assist":{"id":2724,"name":"L. Digne"},"type":"subst","detail":"Substitution 4","comments":null},{"time":{"elapsed":90,"extra":3},"team":{"id":66,"name":"Aston Villa","logo":"https:\/\/media.api-sports.io\/football\/teams\/66.png"},"player":{"id":2724,"name":"Lucas Digne"},"assist":{"id":null,"name":null},"type":"Card","detail":"Yellow Card","comments":"Foul"}],"lineups":[{"team":{"id":49,"name":"Chelsea","logo":"https:\/\/media.api-sports.io\/football\/teams\/49.png","colors":{"player":{"primary":"1532c1","number":"ffffff","border":"1532c1"},"goalkeeper":{"primary":"e3e3e3","number":"000000","border":"e3e3e3"}}},"coach":{"id":12,"name":"G. Potter","photo":"https:\/\/media.api-sports.io\/football\/coachs\/12.png"},"formation":"3-4-2-1","startXI":[{"player":{"id":2273,"name":"Kepa","number":1,"pos":"G","grid":"1:1"}},{"player":{"id":19545,"name":"R. James","number":24,"pos":"D","grid":"2:3"}},{"player":{"id":318,"name":"K. Koulibaly","number":26,"pos":"D","grid":"2:2"}},{"player":{"id":47380,"name":"Marc Cucurella","number":32,"pos":"D","grid":"2:1"}},{"player":{"id":2292,"name":"R. Loftus-Cheek","number":12,"pos":"M","grid":"3:4"}},{"player":{"id":5996,"name":"E. Fern\u00e1ndez","number":5,"pos":"M","grid":"3:3"}},{"player":{"id":2291,"name":"M. Kova\u010di\u0107","number":8,"pos":"M","grid":"3:2"}},{"player":{"id":2933,"name":"B. Chilwell","number":21,"pos":"M","grid":"3:1"}},{"player":{"id":978,"name":"K. Havertz","number":29,"pos":"F","grid":"4:2"}},{"player":{"id":63577,"name":"M. Mudryk","number":15,"pos":"F","grid":"4:1"}},{"player":{"id":583,"name":"Jo\u00e3o F\u00e9lix","number":11,"pos":"F","grid":"5:1"}}],"substitutes":[{"player":{"id":136723,"name":"N. Madueke","number":31,"pos":"F","grid":null}},{"player":{"id":2290,"name":"N. Kant\u00e9","number":7,"pos":"M","grid":null}},{"player":{"id":67972,"name":"C. Gallagher","number":23,"pos":"M","grid":null}},{"player":{"id":17,"name":"C. Puli\u0161i\u0107","number":10,"pos":"M","grid":null}},{"player":{"id":138935,"name":"C. Chukwuemeka","number":30,"pos":"M","grid":null}},{"player":{"id":19012,"name":"M. Bettinelli","number":13,"pos":"G","grid":null}},{"player":{"id":19220,"name":"M. Mount","number":19,"pos":"M","grid":null}},{"player":{"id":19720,"name":"T. Chalobah","number":14,"pos":"D","grid":null}},{"player":{"id":95,"name":"B. Badiashile","number":4,"pos":"D","grid":null}}]},{"team":{"id":66,"name":"Aston Villa","logo":"https:\/\/media.api-sports.io\/football\/teams\/66.png","colors":{"player":{"primary":"88002d","number":"ffffff","border":"88002d"},"goalkeeper":{"primary":"669933","number":"ffffff","border":"669933"}}},"coach":{"id":18,"name":"Unai Emery","photo":"https:\/\/media.api-sports.io\/football\/coachs\/18.png"},"formation":"4-4-2","startXI":[{"player":{"id":19599,"name":"E. Mart\u00ednez","number":1,"pos":"G","grid":"1:1"}},{"player":{"id":894,"name":"A. Young","number":18,"pos":"D","grid":"2:4"}},{"player":{"id":19354,"name":"E. Konsa","number":4,"pos":"D","grid":"2:3"}},{"player":{"id":19179,"name":"T. Mings","number":5,"pos":"D","grid":"2:2"}},{"player":{"id":47547,"name":"\u00c1lex Moreno","number":15,"pos":"D","grid":"2:1"}},{"player":{"id":19191,"name":"J.  McGinn","number":7,"pos":"M","grid":"3:4"}},{"player":{"id":1904,"name":"B. Kamara","number":44,"pos":"M","grid":"3:3"}},{"player":{"id":47522,"name":"Douglas Luiz","number":6,"pos":"M","grid":"3:2"}},{"player":{"id":19192,"name":"J. Ramsey","number":41,"pos":"M","grid":"3:1"}},{"player":{"id":19071,"name":"E. Buend\u00eda","number":10,"pos":"F","grid":"4:2"}},{"player":{"id":19366,"name":"O. Watkins","number":11,"pos":"F","grid":"4:1"}}],"substitutes":[{"player":{"id":19016,"name":"C. Chambers","number":16,"pos":"D","grid":null}},{"player":{"id":983,"name":"L. Bailey","number":31,"pos":"F","grid":null}},{"player":{"id":2922,"name":"L. Dendoncker","number":32,"pos":"M","grid":null}},{"player":{"id":2724,"name":"L. Digne","number":27,"pos":"D","grid":null}},{"player":{"id":671,"name":"B. Traor\u00e9","number":9,"pos":"F","grid":null}},{"player":{"id":13489,"name":"J. Dur\u00e1n","number":22,"pos":"F","grid":null}},{"player":{"id":21090,"name":"Diego Carlos","number":3,"pos":"D","grid":null}},{"player":{"id":284390,"name":"J. Wright","number":64,"pos":"G","grid":null}},{"player":{"id":169291,"name":"V. Sinisalo","number":38,"pos":"G","grid":null}}]}],"statistics":[{"team":{"id":49,"name":"Chelsea","logo":"https:\/\/media.api-sports.io\/football\/teams\/49.png"},"statistics":[{"type":"Shots on Goal","value":8},{"type":"Shots off Goal","value":15},{"type":"Total Shots","value":27},{"type":"Blocked Shots","value":4},{"type":"Shots insidebox","value":19},{"type":"Shots outsidebox","value":8},{"type":"Fouls","value":14},{"type":"Corner Kicks","value":13},{"type":"Offsides","value":2},{"type":"Ball Possession","value":"69%"},{"type":"Yellow Cards","value":3},{"type":"Red Cards","value":null},{"type":"Goalkeeper Saves","value":0},{"type":"Total passes","value":600},{"type":"Passes accurate","value":543},{"type":"Passes %","value":"91%"},{"type":"expected_goals","value":"2.16"}]},{"team":{"id":66,"name":"Aston Villa","logo":"https:\/\/media.api-sports.io\/football\/teams\/66.png"},"statistics":[{"type":"Shots on Goal","value":2},{"type":"Shots off Goal","value":3},{"type":"Total Shots","value":5},{"type":"Blocked Shots","value":0},{"type":"Shots insidebox","value":2},{"type":"Shots outsidebox","value":3},{"type":"Fouls","value":16},{"type":"Corner Kicks","value":2},{"type":"Offsides","value":0},{"type":"Ball Possession","value":"31%"},{"type":"Yellow Cards","value":3},{"type":"Red Cards","value":null},{"type":"Goalkeeper Saves","value":7},{"type":"Total passes","value":285},{"type":"Passes accurate","value":214},{"type":"Passes %","value":"75%"},{"type":"expected_goals","value":"0.92"}]}],"players":[{"team":{"id":49,"name":"Chelsea","logo":"https:\/\/media.api-sports.io\/football\/teams\/49.png","update":"2023-05-30T04:15:23+00:00"},"players":[{"player":{"id":2273,"name":"Kepa Arrizabalaga","photo":"https:\/\/media.api-sports.io\/football\/players\/2273.png"},"statistics":[{"games":{"minutes":90,"number":1,"position":"G","rating":"5.9","captain":false,"substitute":false},"offsides":null,"shots":{"total":null,"on":null},"goals":{"total":null,"conceded":2,"assists":null,"saves":null},"passes":{"total":11,"key":null,"accuracy":"9"},"tackles":{"total":null,"blocks":null,"interceptions":null},"duels":{"total":null,"won":null},"dribbles":{"attempts":null,"success":null,"past":null},"fouls":{"drawn":null,"committed":null},"cards":{"yellow":0,"red":0},"penalty":{"won":null,"commited":null,"scored":0,"missed":0,"saved":0}}]},{"player":{"id":19545,"name":"Reece James","photo":"https:\/\/media.api-sports.io\/football\/players\/19545.png"},"statistics":[{"games":{"minutes":90,"number":24,"position":"D","rating":"7.7","captain":false,"substitute":false},"offsides":null,"shots":{"total":1,"on":null},"goals":{"total":null,"conceded":0,"assists":null,"saves":null},"passes":{"total":91,"key":2,"accuracy":"85"},"tackles":{"total":4,"blocks":null,"interceptions":1},"duels":{"total":8,"won":5},"dribbles":{"attempts":null,"success":null,"past":1},"fouls":{"drawn":1,"committed":null},"cards":{"yellow":0,"red":0},"penalty":{"won":null,"commited":null,"scored":0,"missed":0,"saved":null}}]},{"player":{"id":318,"name":"Kalidou Koulibaly","photo":"https:\/\/media.api-sports.io\/football\/players\/318.png"},"statistics":[{"games":{"minutes":90,"number":26,"position":"D","rating":"7.3","captain":false,"substitute":false},"offsides":null,"shots":{"total":2,"on":null},"goals":{"total":null,"conceded":0,"assists":null,"saves":null},"passes":{"total":69,"key":1,"accuracy":"64"},"tackles":{"total":3,"blocks":null,"interceptions":3},"duels":{"total":10,"won":6},"dribbles":{"attempts":null,"success":null,"past":1},"fouls":{"drawn":null,"committed":null},"cards":{"yellow":0,"red":0},"penalty":{"won":null,"commited":null,"scored":0,"missed":0,"saved":null}}]},{"player":{"id":47380,"name":"Marc Cucurella","photo":"https:\/\/media.api-sports.io\/football\/players\/47380.png"},"statistics":[{"games":{"minutes":80,"number":32,"position":"D","rating":"6.6","captain":false,"substitute":false},"offsides":null,"shots":{"total":1,"on":null},"goals":{"total":null,"conceded":0,"assists":null,"saves":null},"passes":{"total":67,"key":3,"accuracy":"63"},"tackles":{"total":1,"blocks":null,"interceptions":2},"duels":{"total":11,"won":9},"dribbles":{"attempts":null,"success":null,"past":null},"fouls":{"drawn":4,"committed":1},"cards":{"yellow":0,"red":0},"penalty":{"won":null,"commited":null,"scored":0,"missed":0,"saved":null}}]},{"player":{"id":2292,"name":"Ruben Loftus-Cheek","photo":"https:\/\/media.api-sports.io\/football\/players\/2292.png"},"statistics":[{"games":{"minutes":57,"number":12,"position":"M","rating":"6.3","captain":false,"substitute":false},"offsides":null,"shots":{"total":null,"on":null},"goals":{"total":null,"conceded":0,"assists":null,"saves":null},"passes":{"total":44,"key":1,"accuracy":"41"},"tackles":{"total":null,"blocks":null,"interceptions":null},"duels":{"total":7,"won":1},"dribbles":{"attempts":3,"success":null,"past":null},"fouls":{"drawn":1,"committed":1},"cards":{"yellow":0,"red":0},"penalty":{"won":null,"commited":null,"scored":0,"missed":0,"saved":null}}]},{"player":{"id":5996,"name":"Enzo Fern\u00e1ndez","photo":"https:\/\/media.api-sports.io\/football\/players\/5996.png"},"statistics":[{"games":{"minutes":90,"number":5,"position":"M","rating":"7.5","captain":false,"substitute":false},"offsides":null,"shots":{"total":1,"on":null},"goals":{"total":null,"conceded":0,"assists":null,"saves":null},"passes":{"total":74,"key":5,"accuracy":"65"},"tackles":{"total":2,"blocks":null,"interceptions":1},"duels":{"total":13,"won":6},"dribbles":{"attempts":3,"success":3,"past":3},"fouls":{"drawn":null,"committed":3},"cards":{"yellow":1,"red":0},"penalty":{"won":null,"commited":null,"scored":0,"missed":0,"saved":null}}]},{"player":{"id":2291,"name":"Mateo Kova\u010di\u0107","photo":"https:\/\/media.api-sports.io\/football\/players\/2291.png"},"statistics":[{"games":{"minutes":80,"number":8,"position":"M","rating":"7.3","captain":true,"substitute":false},"offsides":null,"shots":{"total":3,"on":null},"goals":{"total":null,"conceded":0,"assists":null,"saves":null},"passes":{"total":71,"key":2,"accuracy":"68"},"tackles":{"total":1,"blocks":null,"interceptions":null},"duels":{"total":10,"won":5},"dribbles":{"attempts":3,"success":2,"past":1},"fouls":{"drawn":1,"committed":1},"cards":{"yellow":1,"red":0},"penalty":{"won":null,"commited":null,"scored":0,"missed":0,"saved":null}}]},{"player":{"id":2933,"name":"Ben Chilwell","photo":"https:\/\/media.api-sports.io\/football\/players\/2933.png"},"statistics":[{"games":{"minutes":90,"number":21,"position":"M","rating":"7.2","captain":false,"substitute":false},"offsides":2,"shots":{"total":4,"on":null},"goals":{"total":null,"conceded":0,"assists":null,"saves":null},"passes":{"total":41,"key":2,"accuracy":"37"},"tackles":{"total":null,"blocks":null,"interceptions":1},"duels":{"total":10,"won":4},"dribbles":{"attempts":3,"success":2,"past":1},"fouls":{"drawn":2,"committed":2},"cards":{"yellow":1,"red":0},"penalty":{"won":null,"commited":null,"scored":0,"missed":0,"saved":null}}]},{"player":{"id":978,"name":"Kai Havertz","photo":"https:\/\/media.api-sports.io\/football\/players\/978.png"},"statistics":[{"games":{"minutes":90,"number":29,"position":"F","rating":"7.3","captain":false,"substitute":false},"offsides":null,"shots":{"total":4,"on":3},"goals":{"total":null,"conceded":0,"assists":null,"saves":null},"passes":{"total":44,"key":3,"accuracy":"37"},"tackles":{"total":null,"blocks":null,"interceptions":null},"duels":{"total":12,"won":6},"dribbles":{"attempts":5,"success":2,"past":1},"fouls":{"drawn":3,"committed":1},"cards":{"yellow":0,"red":0},"penalty":{"won":null,"commited":null,"scored":0,"missed":0,"saved":null}}]},{"player":{"id":63577,"name":"Mykhaylo Mudryk","photo":"https:\/\/media.api-sports.io\/football\/players\/63577.png"},"statistics":[{"games":{"minutes":57,"number":15,"position":"F","rating":"5.9","captain":false,"substitute":false},"offsides":null,"shots":{"total":2,"on":2},"goals":{"total":null,"conceded":0,"assists":null,"saves":null},"passes":{"total":13,"key":null,"accuracy":"12"},"tackles":{"total":1,"blocks":null,"interceptions":null},"duels":{"total":6,"won":1},"dribbles":{"attempts":2,"success":null,"past":null},"fouls":{"drawn":null,"committed":2},"cards":{"yellow":0,"red":0},"penalty":{"won":null,"commited":null,"scored":0,"missed":0,"saved":null}}]},{"player":{"id":583,"name":"Jo\u00e3o F\u00e9lix","photo":"https:\/\/media.api-sports.io\/football\/players\/583.png"},"statistics":[{"games":{"minutes":90,"number":11,"position":"F","rating":"7.3","captain":false,"substitute":false},"offsides":null,"shots":{"total":2,"on":2},"goals":{"total":null,"conceded":0,"assists":null,"saves":null},"passes":{"total":35,"key":1,"accuracy":"30"},"tackles":{"total":2,"blocks":null,"interceptions":null},"duels":{"total":18,"won":10},"dribbles":{"attempts":11,"success":7,"past":null},"fouls":{"drawn":1,"committed":2},"cards":{"yellow":0,"red":0},"penalty":{"won":null,"commited":null,"scored":0,"missed":0,"saved":null}}]},{"player":{"id":19012,"name":"Marcus Bettinelli","photo":"https:\/\/media.api-sports.io\/football\/players\/19012.png"},"statistics":[{"games":{"minutes":null,"number":13,"position":"G","rating":null,"captain":false,"substitute":true},"offsides":null,"shots":{"total":null,"on":null},"goals":{"total":null,"conceded":0,"assists":null,"saves":null},"passes":{"total":null,"key":null,"accuracy":null},"tackles":{"total":null,"blocks":null,"interceptions":null},"duels":{"total":null,"won":null},"dribbles":{"attempts":null,"success":null,"past":null},"fouls":{"drawn":null,"committed":null},"cards":{"yellow":0,"red":0},"penalty":{"won":null,"commited":null,"scored":0,"missed":0,"saved":null}}]},{"player":{"id":19720,"name":"Trevoh Chalobah","photo":"https:\/\/media.api-sports.io\/football\/players\/19720.png"},"statistics":[{"games":{"minutes":null,"number":14,"position":"D","rating":null,"captain":false,"substitute":true},"offsides":null,"shots":{"total":null,"on":null},"goals":{"total":null,"conceded":0,"assists":null,"saves":null},"passes":{"total":null,"key":null,"accuracy":null},"tackles":{"total":null,"blocks":null,"interceptions":null},"duels":{"total":null,"won":null},"dribbles":{"attempts":null,"success":null,"past":null},"fouls":{"drawn":null,"committed":null},"cards":{"yellow":0,"red":0},"penalty":{"won":null,"commited":null,"scored":0,"missed":0,"saved":null}}]},{"player":{"id":95,"name":"Beno\u00eet Badiashile","photo":"https:\/\/media.api-sports.io\/football\/players\/95.png"},"statistics":[{"games":{"minutes":null,"number":4,"position":"D","rating":null,"captain":false,"substitute":true},"offsides":null,"shots":{"total":null,"on":null},"goals":{"total":null,"conceded":0,"assists":null,"saves":null},"passes":{"total":null,"key":null,"accuracy":null},"tackles":{"total":null,"blocks":null,"interceptions":null},"duels":{"total":null,"won":null},"dribbles":{"attempts":null,"success":null,"past":null},"fouls":{"drawn":null,"committed":null},"cards":{"yellow":0,"red":0},"penalty":{"won":null,"commited":null,"scored":0,"missed":0,"saved":null}}]},{"player":{"id":67972,"name":"Conor Gallagher","photo":"https:\/\/media.api-sports.io\/football\/players\/67972.png"},"statistics":[{"games":{"minutes":10,"number":23,"position":"M","rating":"6","captain":false,"substitute":true},"offsides":null,"shots":{"total":null,"on":null},"goals":{"total":null,"conceded":0,"assists":null,"saves":null},"passes":{"total":3,"key":null,"accuracy":"2"},"tackles":{"total":null,"blocks":null,"interceptions":null},"duels":{"total":6,"won":2},"dribbles":{"attempts":2,"success":null,"past":2},"fouls":{"drawn":2,"committed":null},"cards":{"yellow":0,"red":0},"penalty":{"won":null,"commited":null,"scored":0,"missed":0,"saved":null}}]},{"player":{"id":2290,"name":"N'Golo Kant\u00e9","photo":"https:\/\/media.api-sports.io\/football\/players\/2290.png"},"statistics":[{"games":{"minutes":33,"number":7,"position":"M","rating":"6.9","captain":false,"substitute":true},"offsides":null,"shots":{"total":1,"on":null},"goals":{"total":null,"conceded":0,"assists":null,"saves":null},"passes":{"total":21,"key":1,"accuracy":"15"},"tackles":{"total":3,"blocks":null,"interceptions":null},"duels":{"total":6,"won":3},"dribbles":{"attempts":1,"success":null,"past":1},"fouls":{"drawn":null,"committed":1},"cards":{"yellow":0,"red":0},"penalty":{"won":null,"commited":null,"scored":0,"missed":0,"saved":null}}]},{"player":{"id":138935,"name":"Carney Chukwuemeka","photo":"https:\/\/media.api-sports.io\/football\/players\/138935.png"},"statistics":[{"games":{"minutes":null,"number":30,"position":"M","rating":null,"captain":false,"substitute":true},"offsides":null,"shots":{"total":null,"on":null},"goals":{"total":null,"conceded":0,"assists":null,"saves":null},"passes":{"total":null,"key":null,"accuracy":null},"tackles":{"total":null,"blocks":null,"interceptions":null},"duels":{"total":null,"won":null},"dribbles":{"attempts":null,"success":null,"past":null},"fouls":{"drawn":null,"committed":null},"cards":{"yellow":0,"red":0},"penalty":{"won":null,"commited":null,"scored":0,"missed":0,"saved":null}}]},{"player":{"id":19220,"name":"Mason Mount","photo":"https:\/\/media.api-sports.io\/football\/players\/19220.png"},"statistics":[{"games":{"minutes":null,"number":19,"position":"M","rating":null,"captain":false,"substitute":true},"offsides":null,"shots":{"total":null,"on":null},"goals":{"total":null,"conceded":0,"assists":null,"saves":null},"passes":{"total":null,"key":null,"accuracy":null},"tackles":{"total":null,"blocks":null,"interceptions":null},"duels":{"total":null,"won":null},"dribbles":{"attempts":null,"success":null,"past":null},"fouls":{"drawn":null,"committed":null},"cards":{"yellow":0,"red":0},"penalty":{"won":null,"commited":null,"scored":0,"missed":0,"saved":null}}]},{"player":{"id":136723,"name":"Noni Madueke","photo":"https:\/\/media.api-sports.io\/football\/players\/136723.png"},"statistics":[{"games":{"minutes":33,"number":31,"position":"F","rating":"6.9","captain":false,"substitute":true},"offsides":null,"shots":{"total":1,"on":null},"goals":{"total":null,"conceded":0,"assists":null,"saves":null},"passes":{"total":13,"key":2,"accuracy":"13"},"tackles":{"total":1,"blocks":null,"interceptions":1},"duels":{"total":7,"won":4},"dribbles":{"attempts":4,"success":2,"past":null},"fouls":{"drawn":1,"committed":null},"cards":{"yellow":0,"red":0},"penalty":{"won":null,"commited":null,"scored":0,"missed":0,"saved":null}}]},{"player":{"id":17,"name":"Christian Puli\u0161i\u0107","photo":"https:\/\/media.api-sports.io\/football\/players\/17.png"},"statistics":[{"games":{"minutes":10,"number":10,"position":"M","rating":"6.6","captain":false,"substitute":true},"offsides":null,"shots":{"total":1,"on":1},"goals":{"total":null,"conceded":0,"assists":null,"saves":null},"passes":{"total":3,"key":null,"accuracy":"2"},"tackles":{"total":null,"blocks":null,"interceptions":null},"duels":{"total":1,"won":1},"dribbles":{"attempts":null,"success":null,"past":null},"fouls":{"drawn":null,"committed":null},"cards":{"yellow":0,"red":0},"penalty":{"won":null,"commited":null,"scored":0,"missed":0,"saved":null}}]}]},{"team":{"id":66,"name":"Aston Villa","logo":"https:\/\/media.api-sports.io\/football\/teams\/66.png","update":"2023-05-30T04:15:23+00:00"},"players":[{"player":{"id":19599,"name":"Emiliano Mart\u00ednez","photo":"https:\/\/media.api-sports.io\/football\/players\/19599.png"},"statistics":[{"games":{"minutes":90,"number":1,"position":"G","rating":"8.9","captain":false,"substitute":false},"offsides":null,"shots":{"total":null,"on":null},"goals":{"total":null,"conceded":0,"assists":null,"saves":7},"passes":{"total":42,"key":null,"accuracy":"27"},"tackles":{"total":null,"blocks":null,"interceptions":null},"duels":{"total":2,"won":2},"dribbles":{"attempts":null,"success":null,"past":null},"fouls":{"drawn":1,"committed":null},"cards":{"yellow":0,"red":0},"penalty":{"won":null,"commited":null,"scored":0,"missed":0,"saved":0}}]},{"player":{"id":894,"name":"Ashley Young","photo":"https:\/\/media.api-sports.io\/football\/players\/894.png"},"statistics":[{"games":{"minutes":90,"number":18,"position":"D","rating":"6.6","captain":false,"substitute":false},"offsides":null,"shots":{"total":null,"on":null},"goals":{"total":null,"conceded":0,"assists":null,"saves":null},"passes":{"total":20,"key":null,"accuracy":"12"},"tackles":{"total":null,"blocks":1,"interceptions":null},"duels":{"total":10,"won":3},"dribbles":{"attempts":1,"success":null,"past":2},"fouls":{"drawn":3,"committed":1},"cards":{"yellow":0,"red":0},"penalty":{"won":null,"commited":null,"scored":0,"missed":0,"saved":null}}]},{"player":{"id":19354,"name":"Ezri Konsa","photo":"https:\/\/media.api-sports.io\/football\/players\/19354.png"},"statistics":[{"games":{"minutes":90,"number":4,"position":"D","rating":"6.9","captain":false,"substitute":false},"offsides":null,"shots":{"total":null,"on":null},"goals":{"total":null,"conceded":0,"assists":null,"saves":null},"passes":{"total":27,"key":null,"accuracy":"25"},"tackles":{"total":3,"blocks":null,"interceptions":null},"duels":{"total":9,"won":6},"dribbles":{"attempts":null,"success":null,"past":3},"fouls":{"drawn":2,"committed":null},"cards":{"yellow":0,"red":0},"penalty":{"won":null,"commited":null,"scored":0,"missed":0,"saved":null}}]},{"player":{"id":19179,"name":"Tyrone Mings","photo":"https:\/\/media.api-sports.io\/football\/players\/19179.png"},"statistics":[{"games":{"minutes":90,"number":5,"position":"D","rating":"7.3","captain":false,"substitute":false},"offsides":null,"shots":{"total":null,"on":null},"goals":{"total":null,"conceded":0,"assists":null,"saves":null},"passes":{"total":32,"key":null,"accuracy":"29"},"tackles":{"total":null,"blocks":3,"interceptions":1},"duels":{"total":5,"won":2},"dribbles":{"attempts":null,"success":null,"past":1},"fouls":{"drawn":1,"committed":1},"cards":{"yellow":0,"red":0},"penalty":{"won":null,"commited":null,"scored":0,"missed":0,"saved":null}}]},{"player":{"id":47547,"name":"\u00c1lex Moreno","photo":"https:\/\/media.api-sports.io\/football\/players\/47547.png"},"statistics":[{"games":{"minutes":89,"number":15,"position":"D","rating":"7","captain":false,"substitute":false},"offsides":null,"shots":{"total":null,"on":null},"goals":{"total":null,"conceded":0,"assists":null,"saves":null},"passes":{"total":31,"key":null,"accuracy":"27"},"tackles":{"total":3,"blocks":null,"interceptions":1},"duels":{"total":8,"won":5},"dribbles":{"attempts":2,"success":null,"past":null},"fouls":{"drawn":1,"committed":1},"cards":{"yellow":0,"red":0},"penalty":{"won":null,"commited":null,"scored":0,"missed":0,"saved":null}}]},{"player":{"id":19191,"name":"John McGinn","photo":"https:\/\/media.api-sports.io\/football\/players\/19191.png"},"statistics":[{"games":{"minutes":90,"number":7,"position":"M","rating":"7.7","captain":true,"substitute":false},"offsides":null,"shots":{"total":2,"on":1},"goals":{"total":1,"conceded":0,"assists":null,"saves":null},"passes":{"total":16,"key":1,"accuracy":"13"},"tackles":{"total":4,"blocks":null,"interceptions":null},"duels":{"total":23,"won":10},"dribbles":{"attempts":4,"success":4,"past":5},"fouls":{"drawn":1,"committed":3},"cards":{"yellow":0,"red":0},"penalty":{"won":null,"commited":null,"scored":0,"missed":0,"saved":null}}]},{"player":{"id":1904,"name":"Boubacar Kamara","photo":"https:\/\/media.api-sports.io\/football\/players\/1904.png"},"statistics":[{"games":{"minutes":45,"number":44,"position":"M","rating":"6.5","captain":false,"substitute":false},"offsides":null,"shots":{"total":null,"on":null},"goals":{"total":null,"conceded":0,"assists":null,"saves":null},"passes":{"total":11,"key":null,"accuracy":"8"},"tackles":{"total":2,"blocks":null,"interceptions":null},"duels":{"total":5,"won":3},"dribbles":{"attempts":null,"success":null,"past":1},"fouls":{"drawn":null,"committed":1},"cards":{"yellow":1,"red":0},"penalty":{"won":null,"commited":null,"scored":0,"missed":0,"saved":null}}]},{"player":{"id":47522,"name":"Douglas Luiz","photo":"https:\/\/media.api-sports.io\/football\/players\/47522.png"},"statistics":[{"games":{"minutes":87,"number":6,"position":"M","rating":"7","captain":false,"substitute":false},"offsides":null,"shots":{"total":null,"on":null},"goals":{"total":null,"conceded":0,"assists":null,"saves":null},"passes":{"total":29,"key":null,"accuracy":"21"},"tackles":{"total":1,"blocks":null,"interceptions":2},"duels":{"total":9,"won":6},"dribbles":{"attempts":2,"success":1,"past":1},"fouls":{"drawn":1,"committed":1},"cards":{"yellow":0,"red":0},"penalty":{"won":null,"commited":null,"scored":0,"missed":0,"saved":null}}]},{"player":{"id":19192,"name":"Jacob Ramsey","photo":"https:\/\/media.api-sports.io\/football\/players\/19192.png"},"statistics":[{"games":{"minutes":90,"number":41,"position":"M","rating":"7.9","captain":false,"substitute":false},"offsides":null,"shots":{"total":null,"on":null},"goals":{"total":null,"conceded":0,"assists":1,"saves":null},"passes":{"total":26,"key":1,"accuracy":"19"},"tackles":{"total":5,"blocks":1,"interceptions":2},"duels":{"total":18,"won":10},"dribbles":{"attempts":6,"success":2,"past":2},"fouls":{"drawn":2,"committed":1},"cards":{"yellow":0,"red":0},"penalty":{"won":null,"commited":null,"scored":0,"missed":0,"saved":null}}]},{"player":{"id":19071,"name":"Emiliano Buend\u00eda","photo":"https:\/\/media.api-sports.io\/football\/players\/19071.png"},"statistics":[{"games":{"minutes":76,"number":10,"position":"F","rating":"6.5","captain":false,"substitute":false},"offsides":null,"shots":{"total":null,"on":null},"goals":{"total":null,"conceded":0,"assists":null,"saves":null},"passes":{"total":17,"key":1,"accuracy":"15"},"tackles":{"total":1,"blocks":null,"interceptions":1},"duels":{"total":14,"won":4},"dribbles":{"attempts":3,"success":1,"past":2},"fouls":{"drawn":2,"committed":3},"cards":{"yellow":0,"red":0},"penalty":{"won":null,"commited":null,"scored":0,"missed":0,"saved":null}}]},{"player":{"id":19366,"name":"Ollie Watkins","photo":"https:\/\/media.api-sports.io\/football\/players\/19366.png"},"statistics":[{"games":{"minutes":90,"number":11,"position":"F","rating":"6.9","captain":false,"substitute":false},"offsides":null,"shots":{"total":2,"on":1},"goals":{"total":1,"conceded":0,"assists":null,"saves":null},"passes":{"total":17,"key":null,"accuracy":"10"},"tackles":{"total":null,"blocks":null,"interceptions":null},"duels":{"total":13,"won":5},"dribbles":{"attempts":4,"success":2,"past":1},"fouls":{"drawn":null,"committed":2},"cards":{"yellow":0,"red":0},"penalty":{"won":null,"commited":null,"scored":0,"missed":0,"saved":null}}]},{"player":{"id":169291,"name":"Viljami Sinisalo","photo":"https:\/\/media.api-sports.io\/football\/players\/169291.png"},"statistics":[{"games":{"minutes":null,"number":38,"position":"G","rating":null,"captain":false,"substitute":true},"offsides":null,"shots":{"total":null,"on":null},"goals":{"total":null,"conceded":0,"assists":null,"saves":null},"passes":{"total":null,"key":null,"accuracy":null},"tackles":{"total":null,"blocks":null,"interceptions":null},"duels":{"total":null,"won":null},"dribbles":{"attempts":null,"success":null,"past":null},"fouls":{"drawn":null,"committed":null},"cards":{"yellow":0,"red":0},"penalty":{"won":null,"commited":null,"scored":0,"missed":0,"saved":null}}]},{"player":{"id":284390,"name":"James Wright","photo":"https:\/\/media.api-sports.io\/football\/players\/284390.png"},"statistics":[{"games":{"minutes":null,"number":64,"position":"G","rating":null,"captain":false,"substitute":true},"offsides":null,"shots":{"total":null,"on":null},"goals":{"total":null,"conceded":0,"assists":null,"saves":null},"passes":{"total":null,"key":null,"accuracy":null},"tackles":{"total":null,"blocks":null,"interceptions":null},"duels":{"total":null,"won":null},"dribbles":{"attempts":null,"success":null,"past":null},"fouls":{"drawn":null,"committed":null},"cards":{"yellow":0,"red":0},"penalty":{"won":null,"commited":null,"scored":0,"missed":0,"saved":null}}]},{"player":{"id":19016,"name":"Calum Chambers","photo":"https:\/\/media.api-sports.io\/football\/players\/19016.png"},"statistics":[{"games":{"minutes":45,"number":16,"position":"D","rating":"7.3","captain":false,"substitute":true},"offsides":null,"shots":{"total":null,"on":null},"goals":{"total":null,"conceded":0,"assists":null,"saves":null},"passes":{"total":12,"key":1,"accuracy":"6"},"tackles":{"total":5,"blocks":null,"interceptions":1},"duels":{"total":6,"won":5},"dribbles":{"attempts":null,"success":null,"past":null},"fouls":{"drawn":null,"committed":null},"cards":{"yellow":1,"red":0},"penalty":{"won":null,"commited":null,"scored":0,"missed":0,"saved":null}}]},{"player":{"id":2724,"name":"Lucas Digne","photo":"https:\/\/media.api-sports.io\/football\/players\/2724.png"},"statistics":[{"games":{"minutes":1,"number":27,"position":"D","rating":null,"captain":false,"substitute":true},"offsides":null,"shots":{"total":null,"on":null},"goals":{"total":null,"conceded":0,"assists":null,"saves":null},"passes":{"total":2,"key":null,"accuracy":"1"},"tackles":{"total":null,"blocks":null,"interceptions":null},"duels":{"total":1,"won":null},"dribbles":{"attempts":null,"success":null,"past":null},"fouls":{"drawn":null,"committed":1},"cards":{"yellow":1,"red":0},"penalty":{"won":null,"commited":null,"scored":0,"missed":0,"saved":null}}]},{"player":{"id":21090,"name":"Diego Carlos","photo":"https:\/\/media.api-sports.io\/football\/players\/21090.png"},"statistics":[{"games":{"minutes":null,"number":3,"position":"D","rating":null,"captain":false,"substitute":true},"offsides":null,"shots":{"total":null,"on":null},"goals":{"total":null,"conceded":0,"assists":null,"saves":null},"passes":{"total":null,"key":null,"accuracy":null},"tackles":{"total":null,"blocks":null,"interceptions":null},"duels":{"total":null,"won":null},"dribbles":{"attempts":null,"success":null,"past":null},"fouls":{"drawn":null,"committed":null},"cards":{"yellow":0,"red":0},"penalty":{"won":null,"commited":null,"scored":0,"missed":0,"saved":null}}]},{"player":{"id":2922,"name":"Leander Dendoncker","photo":"https:\/\/media.api-sports.io\/football\/players\/2922.png"},"statistics":[{"games":{"minutes":9,"number":32,"position":"M","rating":"6.3","captain":false,"substitute":true},"offsides":null,"shots":{"total":null,"on":null},"goals":{"total":null,"conceded":0,"assists":null,"saves":null},"passes":{"total":null,"key":null,"accuracy":null},"tackles":{"total":null,"blocks":null,"interceptions":null},"duels":{"total":null,"won":null},"dribbles":{"attempts":null,"success":null,"past":null},"fouls":{"drawn":null,"committed":null},"cards":{"yellow":0,"red":0},"penalty":{"won":null,"commited":null,"scored":0,"missed":0,"saved":null}}]},{"player":{"id":13489,"name":"Jhon Dur\u00e1n","photo":"https:\/\/media.api-sports.io\/football\/players\/13489.png"},"statistics":[{"games":{"minutes":null,"number":22,"position":"F","rating":null,"captain":false,"substitute":true},"offsides":null,"shots":{"total":null,"on":null},"goals":{"total":null,"conceded":0,"assists":null,"saves":null},"passes":{"total":null,"key":null,"accuracy":null},"tackles":{"total":null,"blocks":null,"interceptions":null},"duels":{"total":null,"won":null},"dribbles":{"attempts":null,"success":null,"past":null},"fouls":{"drawn":null,"committed":null},"cards":{"yellow":0,"red":0},"penalty":{"won":null,"commited":null,"scored":0,"missed":0,"saved":null}}]},{"player":{"id":671,"name":"Bertrand Traor\u00e9","photo":"https:\/\/media.api-sports.io\/football\/players\/671.png"},"statistics":[{"games":{"minutes":null,"number":9,"position":"F","rating":null,"captain":false,"substitute":true},"offsides":null,"shots":{"total":null,"on":null},"goals":{"total":null,"conceded":0,"assists":null,"saves":null},"passes":{"total":null,"key":null,"accuracy":null},"tackles":{"total":null,"blocks":null,"interceptions":null},"duels":{"total":null,"won":null},"dribbles":{"attempts":null,"success":null,"past":null},"fouls":{"drawn":null,"committed":null},"cards":{"yellow":0,"red":0},"penalty":{"won":null,"commited":null,"scored":0,"missed":0,"saved":null}}]},{"player":{"id":983,"name":"Leon Bailey","photo":"https:\/\/media.api-sports.io\/football\/players\/983.png"},"statistics":[{"games":{"minutes":14,"number":31,"position":"F","rating":"6.6","captain":false,"substitute":true},"offsides":null,"shots":{"total":1,"on":null},"goals":{"total":null,"conceded":0,"assists":null,"saves":null},"passes":{"total":3,"key":null,"accuracy":"1"},"tackles":{"total":null,"blocks":null,"interceptions":null},"duels":{"total":2,"won":1},"dribbles":{"attempts":1,"success":1,"past":null},"fouls":{"drawn":null,"committed":1},"cards":{"yellow":0,"red":0},"penalty":{"won":null,"commited":null,"scored":0,"missed":0,"saved":null}}]}]}]}